{
    "analysis": [
        {
            "Polymer Shape": {
                "molecules": {
                    "POL": {
                        "√⟨Re²⟩": 46.44395424229019,
                        "√⟨Rgxyz²⟩": [
                            10.500761843228984,
                            10.490419760452415,
                            10.397552442133234
                        ],
                        "√⟨Rg²⟩": 18.12247231548763,
                        "⟨Re²⟩/⟨Rg²⟩": 6.567853954344732,
                        "⟨Re⟩": 43.91471915378456,
                        "⟨Rg²⟩": 328.4240028256157,
                        "⟨Rg²⟩-⟨Rg⟩²": 10.3,
                        "⟨Rg⟩": 17.839258515301303
                    }
                },
                "nstep": 10,
                "samples": 4000
            }
        },
        {
            "savestate": {
                "file": "state.json"
            }
        }
    ],
    "compiler": "Clang 10.0.0",
    "energy": [
        {
            "hamiltonian": [
                {
                    "bonded": {
                        "bondlist-intramolecular": [
                            {
                                "harmonic": {
                                    "index": [
                                        0,
                                        1
                                    ],
                                    "k": 100.0,
                                    "req": 5.0
                                }
                            },
                            {
                                "harmonic": {
                                    "index": [
                                        1,
                                        2
                                    ],
                                    "k": 100.0,
                                    "req": 5.0
                                }
                            },
                            {
                                "harmonic": {
                                    "index": [
                                        2,
                                        3
                                    ],
                                    "k": 100.0,
                                    "req": 5.0
                                }
                            },
                            {
                                "harmonic": {
                                    "index": [
                                        3,
                                        4
                                    ],
                                    "k": 100.0,
                                    "req": 5.0
                                }
                            },
                            {
                                "harmonic": {
                                    "index": [
                                        4,
                                        5
                                    ],
                                    "k": 100.0,
                                    "req": 5.0
                                }
                            },
                            {
                                "harmonic": {
                                    "index": [
                                        5,
                                        6
                                    ],
                                    "k": 100.0,
                                    "req": 5.0
                                }
                            },
                            {
                                "harmonic": {
                                    "index": [
                                        6,
                                        7
                                    ],
                                    "k": 100.0,
                                    "req": 5.0
                                }
                            },
                            {
                                "harmonic": {
                                    "index": [
                                        7,
                                        8
                                    ],
                                    "k": 100.0,
                                    "req": 5.0
                                }
                            },
                            {
                                "harmonic": {
                                    "index": [
                                        8,
                                        9
                                    ],
                                    "k": 100.0,
                                    "req": 5.0
                                }
                            },
                            {
                                "harmonic": {
                                    "index": [
                                        9,
                                        10
                                    ],
                                    "k": 100.0,
                                    "req": 5.0
                                }
                            },
                            {
                                "harmonic": {
                                    "index": [
                                        10,
                                        11
                                    ],
                                    "k": 100.0,
                                    "req": 5.0
                                }
                            },
                            {
                                "harmonic": {
                                    "index": [
                                        11,
                                        12
                                    ],
                                    "k": 100.0,
                                    "req": 5.0
                                }
                            },
                            {
                                "harmonic": {
                                    "index": [
                                        12,
                                        13
                                    ],
                                    "k": 100.0,
                                    "req": 5.0
                                }
                            },
                            {
                                "harmonic": {
                                    "index": [
                                        13,
                                        14
                                    ],
                                    "k": 100.0,
                                    "req": 5.0
                                }
                            },
                            {
                                "harmonic": {
                                    "index": [
                                        14,
                                        15
                                    ],
                                    "k": 100.0,
                                    "req": 5.0
                                }
                            },
                            {
                                "harmonic": {
                                    "index": [
                                        15,
                                        16
                                    ],
                                    "k": 100.0,
                                    "req": 5.0
                                }
                            },
                            {
                                "harmonic": {
                                    "index": [
                                        16,
                                        17
                                    ],
                                    "k": 100.0,
                                    "req": 5.0
                                }
                            },
                            {
                                "harmonic": {
                                    "index": [
                                        17,
                                        18
                                    ],
                                    "k": 100.0,
                                    "req": 5.0
                                }
                            },
                            {
                                "harmonic": {
                                    "index": [
                                        18,
                                        19
                                    ],
                                    "k": 100.0,
                                    "req": 5.0
                                }
                            },
                            {
                                "harmonic": {
                                    "index": [
                                        19,
                                        20
                                    ],
                                    "k": 100.0,
                                    "req": 5.0
                                }
                            },
                            {
                                "harmonic": {
                                    "index": [
                                        20,
                                        21
                                    ],
                                    "k": 100.0,
                                    "req": 5.0
                                }
                            },
                            {
                                "harmonic": {
                                    "index": [
                                        21,
                                        22
                                    ],
                                    "k": 100.0,
                                    "req": 5.0
                                }
                            },
                            {
                                "harmonic": {
                                    "index": [
                                        22,
                                        23
                                    ],
                                    "k": 100.0,
                                    "req": 5.0
                                }
                            },
                            {
                                "harmonic": {
                                    "index": [
                                        23,
                                        24
                                    ],
                                    "k": 100.0,
                                    "req": 5.0
                                }
                            },
                            {
                                "harmonic": {
                                    "index": [
                                        24,
                                        25
                                    ],
                                    "k": 100.0,
                                    "req": 5.0
                                }
                            },
                            {
                                "harmonic": {
                                    "index": [
                                        25,
                                        26
                                    ],
                                    "k": 100.0,
                                    "req": 5.0
                                }
                            },
                            {
                                "harmonic": {
                                    "index": [
                                        26,
                                        27
                                    ],
                                    "k": 100.0,
                                    "req": 5.0
                                }
                            },
                            {
                                "harmonic": {
                                    "index": [
                                        27,
                                        28
                                    ],
                                    "k": 100.0,
                                    "req": 5.0
                                }
                            },
                            {
                                "harmonic": {
                                    "index": [
                                        28,
                                        29
                                    ],
                                    "k": 100.0,
                                    "req": 5.0
                                }
                            },
                            {
                                "harmonic": {
                                    "index": [
                                        29,
                                        30
                                    ],
                                    "k": 100.0,
                                    "req": 5.0
                                }
                            },
                            {
                                "harmonic": {
                                    "index": [
                                        30,
                                        31
                                    ],
                                    "k": 100.0,
                                    "req": 5.0
                                }
                            },
                            {
                                "harmonic": {
                                    "index": [
                                        31,
                                        32
                                    ],
                                    "k": 100.0,
                                    "req": 5.0
                                }
                            },
                            {
                                "harmonic": {
                                    "index": [
                                        32,
                                        33
                                    ],
                                    "k": 100.0,
                                    "req": 5.0
                                }
                            },
                            {
                                "harmonic": {
                                    "index": [
                                        33,
                                        34
                                    ],
                                    "k": 100.0,
                                    "req": 5.0
                                }
                            },
                            {
                                "harmonic": {
                                    "index": [
                                        34,
                                        35
                                    ],
                                    "k": 100.0,
                                    "req": 5.0
                                }
                            }
                        ],
                        "relative time": 0.0324838435273608
                    }
                },
                {
                    "nonbonded": {
                        "cutoff_g2g": {
                            "POL POL": null
                        },
                        "pairpot": {
                            "functor potential": {
                                "default": [
                                    {
                                        "hardsphere": {}
                                    }
                                ],
                                "selfenergy": {
                                    "dipole": false,
                                    "monopole": false
                                }
                            }
                        },
                        "relative time": 0.3417576148789959
                    }
                }
            ]
        }
    ],
    "geometry": {
        "length": [
            500.0,
            500.0,
            500.0
        ],
        "type": "cuboid"
    },
    "git revision": "2aac54e7 (2019-10-28)",
    "groups": [
        {
            "POL": {
                "compressible": false,
                "index": [
                    0,
                    35
                ],
                "size": 36
            }
        }
    ],
    "last move": "pivot",
    "moves": [
        {
            "transrot": {
                "acceptance": 0.202,
                "dir": [
                    1.0,
                    1.0,
                    1.0
                ],
                "molecule": "POL",
                "molid": 0,
                "moves": 399710,
                "relative time": 0.0581,
                "relative time (without energy calc)": 0.0103,
                "repeat": 10,
                "√⟨r²⟩": 0.26
            }
        },
        {
            "crankshaft": {
                "acceptance": 0.917,
                "dprot": 0.5,
                "molecule": "POL",
                "moves": 399397,
                "relative time": 0.461,
                "relative time (without energy calc)": 0.0302,
                "repeat": 10,
                "√⟨r_cm²⟩": 0.731
            }
        },
        {
            "pivot": {
                "acceptance": 0.95,
                "dprot": 0.5,
                "molecule": "POL",
                "moves": 400893,
                "relative time": 0.447,
                "relative time (without energy calc)": 0.0333,
                "repeat": 10,
                "√⟨r_cm²⟩": 1.5
            }
        }
    ],
    "number of groups": 1,
    "number of particles": 36,
    "reactionlist": null,
    "relative drift": -3.16328502030316e-12,
    "temperature": 300.0
}
